gmxtop/__init__.py
gmxtop/constants.py
gmxtop/parameterizing.py
gmxtop/parsing.py
gmxtop/utils.py
gmxtop/__pycache__/__init__.cpython-310.pyc
gmxtop/__pycache__/__init__.cpython-311.pyc
gmxtop/__pycache__/__init__.cpython-312.pyc
gmxtop/__pycache__/__init__.cpython-313.pyc
gmxtop/__pycache__/__init__.cpython-314.pyc
gmxtop/__pycache__/constants.cpython-310.pyc
gmxtop/__pycache__/constants.cpython-311.pyc
gmxtop/__pycache__/constants.cpython-312.pyc
gmxtop/__pycache__/constants.cpython-313.pyc
gmxtop/__pycache__/constants.cpython-314.pyc
gmxtop/__pycache__/parameterizing.cpython-310.pyc
gmxtop/__pycache__/parameterizing.cpython-311.pyc
gmxtop/__pycache__/parameterizing.cpython-312.pyc
gmxtop/__pycache__/parameterizing.cpython-313.pyc
gmxtop/__pycache__/parameterizing.cpython-314.pyc
gmxtop/__pycache__/parsing.cpython-310.pyc
gmxtop/__pycache__/parsing.cpython-311.pyc
gmxtop/__pycache__/parsing.cpython-312.pyc
gmxtop/__pycache__/parsing.cpython-313.pyc
gmxtop/__pycache__/parsing.cpython-314.pyc
gmxtop/__pycache__/utils.cpython-310.pyc
gmxtop/__pycache__/utils.cpython-311.pyc
gmxtop/__pycache__/utils.cpython-312.pyc
gmxtop/__pycache__/utils.cpython-313.pyc
gmxtop/__pycache__/utils.cpython-314.pyc
gmxtop/topology/atomic.py
gmxtop/topology/ff.py
gmxtop/topology/topology.py
gmxtop/topology/utils.py
gmxtop/topology/__pycache__/atomic.cpython-310.pyc
gmxtop/topology/__pycache__/atomic.cpython-311.pyc
gmxtop/topology/__pycache__/atomic.cpython-312.pyc
gmxtop/topology/__pycache__/atomic.cpython-313.pyc
gmxtop/topology/__pycache__/atomic.cpython-314.pyc
gmxtop/topology/__pycache__/ff.cpython-310.pyc
gmxtop/topology/__pycache__/ff.cpython-311.pyc
gmxtop/topology/__pycache__/ff.cpython-312.pyc
gmxtop/topology/__pycache__/ff.cpython-313.pyc
gmxtop/topology/__pycache__/ff.cpython-314.pyc
gmxtop/topology/__pycache__/topology.cpython-310.pyc
gmxtop/topology/__pycache__/topology.cpython-311.pyc
gmxtop/topology/__pycache__/topology.cpython-312.pyc
gmxtop-0.0.2.dist-info/licenses/LICENSE
gmxtop-0.0.2.dist-info/METADATA
gmxtop-0.0.2.dist-info/WHEEL
gmxtop-0.0.2.dist-info/top_level.txt
gmxtop-0.0.2.dist-info/RECORD
