Metadata-Version: 2.4
Name: gmxtop
Version: 0.0.2
Summary: Read and write GROMACS topology files and alter associated force fields parameters.
Author: graeter-group
Keywords: GROMACS,topology
Classifier: Programming Language :: Python :: 3
Classifier: Operating System :: OS Independent
Requires-Python: <3.15,>=3.10
License-File: LICENSE
Requires-Dist: numpy
Provides-Extra: dev
Requires-Dist: pytest; extra == "dev"
Requires-Dist: pytest-cov; extra == "dev"
Requires-Dist: pytest-mock; extra == "dev"
Requires-Dist: tox; extra == "dev"
Requires-Dist: tox-uv; extra == "dev"
Requires-Dist: black; extra == "dev"
Requires-Dist: hypothesis; extra == "dev"
Requires-Dist: jupyter; extra == "dev"
Requires-Dist: griffe<1.0.0,>=0.33; extra == "dev"
Requires-Dist: pycallgraph2; extra == "dev"
Requires-Dist: certifi>=2025.6; extra == "dev"
Requires-Dist: jsonschema>=4.24; extra == "dev"
Requires-Dist: jsonschema-specifications>=2025.4; extra == "dev"
Requires-Dist: markdown-it-py>=3.0; extra == "dev"
Requires-Dist: pytz>=2025.2; extra == "dev"
Requires-Dist: referencing>=0.36; extra == "dev"
Requires-Dist: rich>=14.0; extra == "dev"
Requires-Dist: rpds-py>=0.26; extra == "dev"
Requires-Dist: six>=1.17; extra == "dev"
Requires-Dist: typing-extensions>=4.14; extra == "dev"
Requires-Dist: tzdata>=2025.2; extra == "dev"
Requires-Dist: watchdog>=6.0; extra == "dev"
Requires-Dist: zipp>=3.23; extra == "dev"
Dynamic: license-file
